{
  "model_id": "iJN1462",
  "species_directory": "pseudomonas_putida_iJN1462",
  "start_time": "2025-06-09 16:40:41",
  "input_file": "iJN1462_input.xml",
  "output_file": "iJN1462_processed.xml",
  "problems_detected": [],
  "warnings": [],
  "conversion_summary": {
    "model_id": "iJN1462",
    "total_metabolites": 2145,
    "successful_conversions": 1615,
    "metanetx_conversions": 1615,
    "unchanged_metabolites": 530,
    "failed_conversions": 0,
    "encoding_fixes_applied": 0,
    "conversion_rate": 75.3,
    "metanetx_rate": 75.3
  },
  "sbml_read_mode": "standard",
  "pattern_detected": "bigg_kegg_metanetx_seed",
  "databases_found": ["metanetx", "bigg", "seed", "kegg"],
  "metabolites_total": 2145,
  "conversion_log_files": {
    "statistics": {
      "model_id": "iJN1462",
      "total_metabolites": 2145,
      "successful_conversions": 1615,
      "metanetx_conversions": 1615,
      "unchanged_metabolites": 530,
      "failed_conversions": 0,
      "encoding_fixes_applied": 0,
      "conversion_rate": 75.3,
      "metanetx_rate": 75.3
    },
    "log_file": "/projectnb/talbot-lab-data/zrwerbin/soil_microbe_GEMs/species/pseudomonas_putida_iJN1462/conversion_logs/iJN1462_metabolite_conversions.csv",
    "summary_file": "/projectnb/talbot-lab-data/zrwerbin/soil_microbe_GEMs/species/pseudomonas_putida_iJN1462/conversion_logs/iJN1462_conversion_summary.json"
  },
  "end_time": "2025-06-09 16:41:26",
  "processing_time_seconds": 44.8742,
  "success": true
}
